solweig_gpu/Tgmaps_v1.py
solweig_gpu/__init__.py
solweig_gpu/calculate_utci.py
solweig_gpu/cli.py
solweig_gpu/landcoverclasses_2016a.txt
solweig_gpu/preprocessor.py
solweig_gpu/shadow.py
solweig_gpu/solweig.py
solweig_gpu/solweig_gpu.py
solweig_gpu/solweig_gpu_gui.py
solweig_gpu/sun_position.py
solweig_gpu/utci_process.py
solweig_gpu/walls_aspect.py
solweig_gpu-1.2.20.dist-info/licenses/LICENSE
tests/__init__.py
tests/conftest.py
tests/test_calculate_utci.py
tests/test_cli.py
tests/test_era5_processing.py
tests/test_gpu_smoke.py
tests/test_integration.py
tests/test_integration_end_to_end.py
tests/test_preprocessor.py
tests/test_sun_position.py
tests/test_tiling_and_metfiles.py
tests/test_walls_aspect.py
tests/test_wrf_and_gui.py
solweig_gpu-1.2.20.dist-info/METADATA
solweig_gpu-1.2.20.dist-info/WHEEL
solweig_gpu-1.2.20.dist-info/entry_points.txt
solweig_gpu-1.2.20.dist-info/top_level.txt
solweig_gpu-1.2.20.dist-info/RECORD
