Metadata-Version: 2.4
Name: solweig-gpu
Version: 1.2.20
Summary: GPU-accelerated SOLWEIG model for urban thermal comfort simulation
Home-page: https://github.com/nvnsudharsan/SOLWEIG-GPU
Author: Harsh Kamath, Naveen Sudharsan
Author-email: harsh.kamath@utexas.edu, naveens@utexas.edu
License: GPL-3.0-only
Classifier: License :: OSI Approved :: GNU General Public License v3 (GPLv3)
Classifier: Programming Language :: Python :: 3
Classifier: Operating System :: POSIX :: Linux
Classifier: Intended Audience :: Science/Research
Classifier: Topic :: Scientific/Engineering :: Atmospheric Science
Requires-Python: >=3.10
License-File: LICENSE
Requires-Dist: torch
Requires-Dist: numpy
Requires-Dist: scipy
Requires-Dist: pandas
Requires-Dist: netCDF4
Requires-Dist: pytz
Requires-Dist: shapely
Requires-Dist: timezonefinder
Requires-Dist: gdal
Requires-Dist: xarray
Requires-Dist: tqdm
Requires-Dist: PyQt5
Requires-Dist: matplotlib
Dynamic: author
Dynamic: author-email
Dynamic: classifier
Dynamic: description
Dynamic: description-content-type
Dynamic: home-page
Dynamic: license
Dynamic: license-file
Dynamic: requires-dist
Dynamic: requires-python
Dynamic: summary
